calcli.py
calcli-1.0.0.dist-info/licenses/LICENSE
calcli-1.0.0.dist-info/METADATA
calcli-1.0.0.dist-info/WHEEL
calcli-1.0.0.dist-info/entry_points.txt
calcli-1.0.0.dist-info/top_level.txt
calcli-1.0.0.dist-info/RECORD
