Metadata-Version: 2.4
Name: calcli
Version: 1.0.0
Summary: A simple, elegant terminal calculator with interactive mode
Home-page: https://github.com/tolaoyelola/calcli
Author: Tola Oyelola
Author-email: tola@ootola.com
Classifier: Programming Language :: Python :: 3
Classifier: License :: OSI Approved :: MIT License
Classifier: Operating System :: OS Independent
Classifier: Development Status :: 4 - Beta
Classifier: Intended Audience :: Developers
Classifier: Topic :: Utilities
Requires-Python: >=3.8
License-File: LICENSE
Requires-Dist: colorama>=0.4.3
Requires-Dist: pyperclip>=1.8.2
Dynamic: author
Dynamic: author-email
Dynamic: classifier
Dynamic: description
Dynamic: description-content-type
Dynamic: home-page
Dynamic: license-file
Dynamic: requires-dist
Dynamic: requires-python
Dynamic: summary
